.DS_Store
optimiz/__init__.py
optimiz/coordinate_descent.py
optimiz/gradient_descent.py
optimiz/linear_model.py
optimiz/logger.py
optimiz/losses.py
optimiz/nesterov_accelerated_gradient_descent.py
optimiz/newtons_method.py
optimiz/optimizer.py
optimiz/optimizer_factory.py
optimiz/preprocessing.py
optimiz/proximal_gradient_descent.py
optimiz/stochastic_gradient_descent.py
optimiz/utils.py
optimiz-1.0.1.dist-info/METADATA
optimiz-1.0.1.dist-info/WHEEL
optimiz-1.0.1.dist-info/top_level.txt
optimiz-1.0.1.dist-info/RECORD
