Metadata-Version: 2.1
Name: optimiz
Version: 1.0.1
Summary: A simple optimization library for machine learning
Home-page: https://github.com/gangradeamitesh/optimiz_it.git
Author: Amitesh Gangrade
Author-email: gangradeamitesh@gmail.com
Classifier: Programming Language :: Python :: 3
Classifier: License :: OSI Approved :: MIT License
Classifier: Operating System :: OS Independent
Requires-Python: >=3.6
Requires-Dist: numpy
Requires-Dist: matplotlib
